setup.cfg
setup.py
dhis/__init__.py
dhis/config.py
dhis/configuration.py
dhis/database.py
dhis/endpoint.py
dhis/secrets.py
dhis/server.py
dhis/sql.py
dhis/utils.py
dhis.egg-info/PKG-INFO
dhis.egg-info/SOURCES.txt
dhis.egg-info/dependency_links.txt
dhis.egg-info/not-zip-safe
dhis.egg-info/requires.txt
dhis.egg-info/top_level.txt
dhis/types/__init__.py
dhis/types/types.py