Metadata-Version: 1.0
Name: dhis
Version: 0.1.2
Summary: Utilities for working with DHIS2
Home-page: https://github.com/dhis2/dhis2-python
Author: DHIS2 Development Team
Author-email: post@dhis2.org
License: BSD
Platform: UNKNOWN
